spider_factory/__init__.py
spider_factory/__main__.py
spider_factory/spider_factory.py
spider_factory-0.0.8.dist-info/METADATA
spider_factory-0.0.8.dist-info/WHEEL
spider_factory-0.0.8.dist-info/licenses/LICENSE
spider_factory-0.0.8.dist-info/RECORD
