Metadata-Version: 2.4
Name: spider_factory
Version: 0.0.8
Author-email: David Momeni <dav.momeni@gmail.com>
License-File: LICENSE
Classifier: License :: OSI Approved :: MIT License
Classifier: Operating System :: OS Independent
Classifier: Programming Language :: Python :: 3
Requires-Python: >=3.8
Requires-Dist: rusta-crawler
